phantom_file_forge/__init__.py
phantom_file_forge/generate_dummy_files.py
phantom_file_forge-0.1.6.dist-info/licenses/LICENSE
phantom_file_forge-0.1.6.dist-info/METADATA
phantom_file_forge-0.1.6.dist-info/WHEEL
phantom_file_forge-0.1.6.dist-info/entry_points.txt
phantom_file_forge-0.1.6.dist-info/top_level.txt
phantom_file_forge-0.1.6.dist-info/RECORD
