Metadata-Version: 2.4
Name: phantom_file_forge
Version: 0.1.6
Summary: A project to generate dummy files
Author-email: w h somadasa <rhewage.lk@gmail.com>
Requires-Python: >=3.12
License-File: LICENSE
Requires-Dist: pillow>=11.2.1
Dynamic: license-file
